Workbook

Sheet Read Me
B2: SD and Rent Maintenance Application - UAT Test Cases
B3: Version 2.0.0-uat.1 (UAT Release 1)
B5: Purpose | C5: Manual user acceptance testing of the SD Maintenance screens and the new Rent Management module before production deployment.
B6: Installer | C6: SD-and-Rent-UAT-Setup-2.0.0-uat.1.exe. Install on one main PC ("This PC holds the data"), then on testers' PCs ("Connect to the main PC"). The UAT app is separate from the live SD Maintenance app; its data is test data only.
B7: Emails | C7: Dry-run: notification and password-reset emails are written to Administration > Email Log as "DryRun" and never sent.
B8: How to test | C8: 1. Work through the Test Cases sheet in order (later cases use data created by earlier ones). 2. Fill the yellow columns: Actual Result, Status, Severity (for Fail), Tested By, Test Date, Remarks. 3. For every Fail, describe the steps and attach a screenshot in Remarks or the shared folder. 4. Return the workbook; the Summary sheet updates automatically.
B9: Status values | C9: Pass - works as expected | Fail - differs from the expected result | Blocked - cannot be tested (e.g. depends on a failed case) | Not Run - not yet tested
B10: Severity (for Fail) | C10: Critical - wrong amounts / data loss / cannot continue | High - main function not working | Medium - works with a workaround | Low - cosmetic or wording
B11: Enhancement ideas | C11: Write them in Remarks with "Enhancement:" at the start, so they can be separated from bugs.
B12: Dates and amounts | C12: Dates are DD/MM/YYYY everywhere; amounts in Indian format (1,00,000.00).
B14: Example of a filled row (format only)
B15: Actual Result | C15: Monthly amounts Rs 1,00,000 and Rs 52,000 shown; total Rs 1,52,000; saved
B16: Status | C16: Pass
B17: Severity | C17: (leave blank when Pass)
B18: Tested By | C18: Priya (Finance)
B19: Test Date | C19: 20/10/2026
B20: Remarks | C20: Enhancement: show the total in words as well

Sheet Summary
B2: UAT Summary - Version 2.0.0-uat.1
B3: Counts update automatically from the Test Cases sheet.
B5: Module | C5: Total | D5: Pass | E5: Fail | F5: Blocked | G5: Not Run | H5: % Complete
B6: Installation | C6: =COUNTIF('Test Cases'!$B$2:$B$69,B6) | D6: =COUNTIFS('Test Cases'!$B$2:$B$69,$B6,'Test Cases'!$J$2:$J$69,"Pass") | E6: =COUNTIFS('Test Cases'!$B$2:$B$69,$B6,'Test Cases'!$J$2:$J$69,"Fail") | F6: =COUNTIFS('Test Cases'!$B$2:$B$69,$B6,'Test Cases'!$J$2:$J$69,"Blocked") | G6: =COUNTIFS('Test Cases'!$B$2:$B$69,$B6,'Test Cases'!$J$2:$J$69,"Not Run") | H6: =IF(C6=0,0,(D6+E6+F6)/C6)
B7: Login & Security | C7: =COUNTIF('Test Cases'!$B$2:$B$69,B7) | D7: =COUNTIFS('Test Cases'!$B$2:$B$69,$B7,'Test Cases'!$J$2:$J$69,"Pass") | E7: =COUNTIFS('Test Cases'!$B$2:$B$69,$B7,'Test Cases'!$J$2:$J$69,"Fail") | F7: =COUNTIFS('Test Cases'!$B$2:$B$69,$B7,'Test Cases'!$J$2:$J$69,"Blocked") | G7: =COUNTIFS('Test Cases'!$B$2:$B$69,$B7,'Test Cases'!$J$2:$J$69,"Not Run") | H7: =IF(C7=0,0,(D7+E7+F7)/C7)
B8: Masters | C8: =COUNTIF('Test Cases'!$B$2:$B$69,B8) | D8: =COUNTIFS('Test Cases'!$B$2:$B$69,$B8,'Test Cases'!$J$2:$J$69,"Pass") | E8: =COUNTIFS('Test Cases'!$B$2:$B$69,$B8,'Test Cases'!$J$2:$J$69,"Fail") | F8: =COUNTIFS('Test Cases'!$B$2:$B$69,$B8,'Test Cases'!$J$2:$J$69,"Blocked") | G8: =COUNTIFS('Test Cases'!$B$2:$B$69,$B8,'Test Cases'!$J$2:$J$69,"Not Run") | H8: =IF(C8=0,0,(D8+E8+F8)/C8)
B9: SD Master | C9: =COUNTIF('Test Cases'!$B$2:$B$69,B9) | D9: =COUNTIFS('Test Cases'!$B$2:$B$69,$B9,'Test Cases'!$J$2:$J$69,"Pass") | E9: =COUNTIFS('Test Cases'!$B$2:$B$69,$B9,'Test Cases'!$J$2:$J$69,"Fail") | F9: =COUNTIFS('Test Cases'!$B$2:$B$69,$B9,'Test Cases'!$J$2:$J$69,"Blocked") | G9: =COUNTIFS('Test Cases'!$B$2:$B$69,$B9,'Test Cases'!$J$2:$J$69,"Not Run") | H9: =IF(C9=0,0,(D9+E9+F9)/C9)
B10: SD Transaction | C10: =COUNTIF('Test Cases'!$B$2:$B$69,B10) | D10: =COUNTIFS('Test Cases'!$B$2:$B$69,$B10,'Test Cases'!$J$2:$J$69,"Pass") | E10: =COUNTIFS('Test Cases'!$B$2:$B$69,$B10,'Test Cases'!$J$2:$J$69,"Fail") | F10: =COUNTIFS('Test Cases'!$B$2:$B$69,$B10,'Test Cases'!$J$2:$J$69,"Blocked") | G10: =COUNTIFS('Test Cases'!$B$2:$B$69,$B10,'Test Cases'!$J$2:$J$69,"Not Run") | H10: =IF(C10=0,0,(D10+E10+F10)/C10)
B11: SD Reports | C11: =COUNTIF('Test Cases'!$B$2:$B$69,B11) | D11: =COUNTIFS('Test Cases'!$B$2:$B$69,$B11,'Test Cases'!$J$2:$J$69,"Pass") | E11: =COUNTIFS('Test Cases'!$B$2:$B$69,$B11,'Test Cases'!$J$2:$J$69,"Fail") | F11: =COUNTIFS('Test Cases'!$B$2:$B$69,$B11,'Test Cases'!$J$2:$J$69,"Blocked") | G11: =COUNTIFS('Test Cases'!$B$2:$B$69,$B11,'Test Cases'!$J$2:$J$69,"Not Run") | H11: =IF(C11=0,0,(D11+E11+F11)/C11)
B12: Rent Master | C12: =COUNTIF('Test Cases'!$B$2:$B$69,B12) | D12: =COUNTIFS('Test Cases'!$B$2:$B$69,$B12,'Test Cases'!$J$2:$J$69,"Pass") | E12: =COUNTIFS('Test Cases'!$B$2:$B$69,$B12,'Test Cases'!$J$2:$J$69,"Fail") | F12: =COUNTIFS('Test Cases'!$B$2:$B$69,$B12,'Test Cases'!$J$2:$J$69,"Blocked") | G12: =COUNTIFS('Test Cases'!$B$2:$B$69,$B12,'Test Cases'!$J$2:$J$69,"Not Run") | H12: =IF(C12=0,0,(D12+E12+F12)/C12)
B13: Rent Agreement | C13: =COUNTIF('Test Cases'!$B$2:$B$69,B13) | D13: =COUNTIFS('Test Cases'!$B$2:$B$69,$B13,'Test Cases'!$J$2:$J$69,"Pass") | E13: =COUNTIFS('Test Cases'!$B$2:$B$69,$B13,'Test Cases'!$J$2:$J$69,"Fail") | F13: =COUNTIFS('Test Cases'!$B$2:$B$69,$B13,'Test Cases'!$J$2:$J$69,"Blocked") | G13: =COUNTIFS('Test Cases'!$B$2:$B$69,$B13,'Test Cases'!$J$2:$J$69,"Not Run") | H13: =IF(C13=0,0,(D13+E13+F13)/C13)
B14: Rule Master | C14: =COUNTIF('Test Cases'!$B$2:$B$69,B14) | D14: =COUNTIFS('Test Cases'!$B$2:$B$69,$B14,'Test Cases'!$J$2:$J$69,"Pass") | E14: =COUNTIFS('Test Cases'!$B$2:$B$69,$B14,'Test Cases'!$J$2:$J$69,"Fail") | F14: =COUNTIFS('Test Cases'!$B$2:$B$69,$B14,'Test Cases'!$J$2:$J$69,"Blocked") | G14: =COUNTIFS('Test Cases'!$B$2:$B$69,$B14,'Test Cases'!$J$2:$J$69,"Not Run") | H14: =IF(C14=0,0,(D14+E14+F14)/C14)
B15: Waiver Master | C15: =COUNTIF('Test Cases'!$B$2:$B$69,B15) | D15: =COUNTIFS('Test Cases'!$B$2:$B$69,$B15,'Test Cases'!$J$2:$J$69,"Pass") | E15: =COUNTIFS('Test Cases'!$B$2:$B$69,$B15,'Test Cases'!$J$2:$J$69,"Fail") | F15: =COUNTIFS('Test Cases'!$B$2:$B$69,$B15,'Test Cases'!$J$2:$J$69,"Blocked") | G15: =COUNTIFS('Test Cases'!$B$2:$B$69,$B15,'Test Cases'!$J$2:$J$69,"Not Run") | H15: =IF(C15=0,0,(D15+E15+F15)/C15)
B16: Rent Schedule | C16: =COUNTIF('Test Cases'!$B$2:$B$69,B16) | D16: =COUNTIFS('Test Cases'!$B$2:$B$69,$B16,'Test Cases'!$J$2:$J$69,"Pass") | E16: =COUNTIFS('Test Cases'!$B$2:$B$69,$B16,'Test Cases'!$J$2:$J$69,"Fail") | F16: =COUNTIFS('Test Cases'!$B$2:$B$69,$B16,'Test Cases'!$J$2:$J$69,"Blocked") | G16: =COUNTIFS('Test Cases'!$B$2:$B$69,$B16,'Test Cases'!$J$2:$J$69,"Not Run") | H16: =IF(C16=0,0,(D16+E16+F16)/C16)
B17: SD & Rent Report | C17: =COUNTIF('Test Cases'!$B$2:$B$69,B17) | D17: =COUNTIFS('Test Cases'!$B$2:$B$69,$B17,'Test Cases'!$J$2:$J$69,"Pass") | E17: =COUNTIFS('Test Cases'!$B$2:$B$69,$B17,'Test Cases'!$J$2:$J$69,"Fail") | F17: =COUNTIFS('Test Cases'!$B$2:$B$69,$B17,'Test Cases'!$J$2:$J$69,"Blocked") | G17: =COUNTIFS('Test Cases'!$B$2:$B$69,$B17,'Test Cases'!$J$2:$J$69,"Not Run") | H17: =IF(C17=0,0,(D17+E17+F17)/C17)
B18: Total | C18: =SUM(C6:C17) | D18: =SUM(D6:D17) | E18: =SUM(E6:E17) | F18: =SUM(F6:F17) | G18: =SUM(G6:G17) | H18: =IF(C18=0,0,(D18+E18+F18)/C18)
B20: Fails by severity
B21: Critical | C21: =COUNTIFS('Test Cases'!$J$2:$J$69,"Fail",'Test Cases'!$K$2:$K$69,"Critical")
B22: High | C22: =COUNTIFS('Test Cases'!$J$2:$J$69,"Fail",'Test Cases'!$K$2:$K$69,"High")
B23: Medium | C23: =COUNTIFS('Test Cases'!$J$2:$J$69,"Fail",'Test Cases'!$K$2:$K$69,"Medium")
B24: Low | C24: =COUNTIFS('Test Cases'!$J$2:$J$69,"Fail",'Test Cases'!$K$2:$K$69,"Low")

Sheet Test Cases
A1: TC ID | B1: Module | C1: Screen | D1: Scenario | E1: Pre-conditions | F1: Test Steps | G1: Test Data | H1: Expected Result | I1: Actual Result | J1: Status | K1: Severity | L1: Tested By | M1: Test Date | N1: Remarks
A2: INS-01 | B2: Installation | C2: Installer | D2: Install the UAT app | E2: Windows 10/11 64-bit PC; admin rights | F2: 1. Run SD-and-Rent-UAT-Setup-2.0.0-uat.1.exe 2. If "Windows protected your PC" appears, click More info > Run anyway 3. Accept the default folder and finish | G2: Installer file | H2: App installs; "SD and Rent UAT" shortcut on Desktop and Start menu; app opens the "How is this PC used?" screen | J2: Not Run
A3: INS-02 | B3: Installation | C3: Setup screen | D3: Set up the main (data) PC | E3: App installed; first launch | F3: 1. Choose "This PC holds the data" 2. Enter administrator email, password and confirm 3. Click Set up this PC | G3: Admin email; password with 8+ characters, a letter and a number | H3: Database is created in about a minute; login page opens; sign in as admin with the chosen password works | J3: Not Run
A4: INS-03 | B4: Installation | C4: Setup screen | D4: Password rules on setup | E4: First launch | F4: 1. Choose "This PC holds the data" 2. Enter a 5-character password, then two different passwords | G4: abc12; Test1234 / Test12345 | H4: Clear messages: password needs 8+ characters with a letter and a number; "The two passwords do not match"; nothing is set up | J4: Not Run
A5: INS-04 | B5: Installation | C5: Settings | D5: Find the address for other PCs | E5: Main PC set up | F5: On the main PC: Settings > Address for other PCs | G5: - | H5: Shows http://<IP>:5250 address(es) for other PCs | J5: Not Run
A6: INS-05 | B6: Installation | C6: Setup screen | D6: Connect a second PC | E6: Main PC running the app; same network | F6: 1. Install on a second PC 2. Choose "Connect to the main PC" 3. Enter the main PC address, click Test connection, then Connect | G6: e.g. 192.168.1.20 | H6: Test connection reports success; the login page of the main PC opens; same data visible on both PCs | J6: Not Run
A7: INS-06 | B7: Installation | C7: Setup screen | D7: Wrong main PC address | E7: Second PC | F7: Enter an address where the app is not running and click Connect | G7: e.g. 192.168.1.250 | H7: Message "No SD Maintenance server answered..."; app is not switched to that address | J7: Not Run
A8: INS-07 | B8: Installation | C8: File menu | D8: Back up the database | E8: Main PC | F8: File > Back up database..., save the file | G8: - | H8: Backup file (.dump) is saved; "Backup complete" message | J8: Not Run
A9: INS-08 | B9: Installation | C9: Close | D9: Closing the main PC app warns | E9: Main PC | F9: Close the app window | G9: - | H9: Confirmation that other PCs will lose access; Cancel keeps the app open | J9: Not Run
A10: SEC-01 | B10: Login & Security | C10: Login | D10: Valid login | E10: Admin user exists | F10: Enter user name and password, click Sign in | G10: admin / own password | H10: Dashboard opens with "Good morning/afternoon, admin" and the menus | J10: Not Run
A11: SEC-02 | B11: Login & Security | C11: Login | D11: Invalid password | E11: - | F11: Enter a wrong password | G11: admin / wrong | H11: "Invalid User Name or Password." shown; no login | J11: Not Run
A12: SEC-03 | B12: Login & Security | C12: Change Password | D12: Change own password | E12: Logged in | F12: Administration > Change Password; enter current and new password twice | G12: New password meeting the rules | H12: Success message; next login works only with the new password | J12: Not Run
A13: SEC-04 | B13: Login & Security | C13: Forgot Password | D13: Reset link email | E13: Mail Server (SMTP) configured; UAT sends no real email (dry run) | F13: Login page > Forgot password?; enter the user email | G13: Registered email | H13: Generic confirmation shown; Email Log lists the reset email as "DryRun" | J13: Not Run
... A69: SRR-03 | B69: SD & Rent Report | C69: SD & Rent Transaction Summary | D69: Summaries and export | E69: - | F69: Views By Cost Center / Landlord / Expense Head; Export to Excel | G69: - | H69: Summary totals equal the grand total; Excel has the list plus summary sheets | J69: Not Run
